[
 {
  "hid":519,
  "sid":"estimation_velocity",
  "rsid":"estimation_velocity",
  "esid":"motion_controller:3",
  "parent":512,
  "children":[
   520
  ],
  "name":"Velocity Estimator (estimation_velocity)",
  "fullname":"AMC_BLDC/Motion Controller Single (motion_controller_single)/Motion Controller (motion_controller)/Estimation/Velocity Estimator (estimation_velocity)",
  "label":"Velocity Estimator (estimation_velocity)",
  "className":"Simulink.ModelReference",
  "icon":"MdlRefBlockIcon_icon",
  "svg":"support/slwebview_files/estimation_velocity_d.svg",
  "thumbnail":"support/slwebview_files/estimation_velocity_d.png",
  "elements":[
   {
    "sid":"estimation_velocity:293",
    "rsid":"estimation_velocity:293",
    "name":"EstimationConfig",
    "label":"EstimationConfig",
    "className":"Simulink.Inport",
    "icon":"BlockIcon_icon"
   },
   {
    "sid":"estimation_velocity:298",
    "rsid":"estimation_velocity:298",
    "name":"position",
    "label":"position",
    "className":"Simulink.Inport",
    "icon":"BlockIcon_icon"
   },
   {
    "sid":"estimation_velocity:291",
    "rsid":"estimation_velocity:291",
    "name":"Constant",
    "label":"Constant",
    "className":"Simulink.Constant",
    "icon":"BlockIcon_icon"
   },
   {
    "sid":"estimation_velocity:290",
    "rsid":"estimation_velocity:290",
    "name":"Delay",
    "label":"Delay",
    "className":"Simulink.Delay",
    "icon":"BlockIcon_icon"
   },
   {
    "sid":"estimation_velocity:280",
    "rsid":"estimation_velocity:280",
    "name":"Delay Line",
    "label":"Delay Line",
    "className":"Simulink.SFunction",
    "icon":"BlockIcon_icon"
   },
   {
    "sid":"estimation_velocity:282",
    "rsid":"estimation_velocity:282",
    "name":"Frame Conversion",
    "label":"Frame Conversion",
    "className":"Simulink.FrameConversion",
    "icon":"BlockIcon_icon"
   },
   {
    "sid":"estimation_velocity:283",
    "rsid":"estimation_velocity:283",
    "name":"Gain",
    "label":"Gain",
    "className":"Simulink.Gain",
    "icon":"BlockIcon_icon"
   },
   {
    "sid":"estimation_velocity:292",
    "rsid":"estimation_velocity:292",
    "name":"Index\nVector",
    "label":"Index Vector",
    "className":"Simulink.MultiPortSwitch",
    "icon":"BlockIcon_icon"
   },
   {
    "sid":"estimation_velocity:284",
    "rsid":"estimation_velocity:284",
    "name":"Least Squares\nPolynomial Fit",
    "label":"Least Squares Polynomial Fit",
    "className":"Least Squares Polynomial Fit",
    "icon":"BlockIcon_icon"
   },
   {
    "sid":"estimation_velocity:285",
    "rsid":"estimation_velocity:285",
    "name":"Selector",
    "label":"Selector",
    "className":"Simulink.Selector",
    "icon":"BlockIcon_icon"
   },
   {
    "sid":"estimation_velocity:286",
    "rsid":"estimation_velocity:286",
    "name":"Sum",
    "label":"Sum",
    "className":"Simulink.Sum",
    "icon":"BlockIcon_icon"
   },
   {
    "sid":"estimation_velocity:299",
    "rsid":"estimation_velocity:299",
    "name":"tp5be0e858_c436_45a9_88fb_67d9e1166a0f",
    "label":"tp5be0e858_c436_45a9_88fb_67d9e1166a0f",
    "className":"Simulink.FrameConversion",
    "icon":"BlockIcon_icon"
   },
   {
    "sid":"estimation_velocity:235",
    "rsid":"estimation_velocity:235",
    "name":"EstimatedVelocity",
    "label":"EstimatedVelocity",
    "className":"Simulink.Outport",
    "icon":"BlockIcon_icon"
   },
   {
    "sid":"estimation_velocity:298#out:1;line",
    "rsid":"estimation_velocity:298#out:1;line",
    "name":"",
    "label":"",
    "className":"Simulink.Line",
    "icon":"LineIcon_icon"
   },
   {
    "sid":"estimation_velocity:286#out:1;line",
    "rsid":"estimation_velocity:286#out:1;line",
    "name":"",
    "label":"",
    "className":"Simulink.Line",
    "icon":"LineIcon_icon"
   },
   {
    "sid":"estimation_velocity:284#out:1;line",
    "rsid":"estimation_velocity:284#out:1;line",
    "name":"",
    "label":"",
    "className":"Simulink.Line",
    "icon":"LineIcon_icon"
   },
   {
    "sid":"estimation_velocity:290#out:1;line",
    "rsid":"estimation_velocity:290#out:1;line",
    "name":"",
    "label":"",
    "className":"Simulink.Line",
    "icon":"LineIcon_icon"
   },
   {
    "sid":"estimation_velocity:282#out:1;line",
    "rsid":"estimation_velocity:282#out:1;line",
    "name":"",
    "label":"",
    "className":"Simulink.Line",
    "icon":"LineIcon_icon"
   },
   {
    "sid":"estimation_velocity:283#out:1;line",
    "rsid":"estimation_velocity:283#out:1;line",
    "name":"v_avg",
    "label":"v_avg",
    "className":"Simulink.Line",
    "icon":"LineIcon_icon"
   },
   {
    "sid":"estimation_velocity:285#out:1;line",
    "rsid":"estimation_velocity:285#out:1;line",
    "name":"v_ls",
    "label":"v_ls",
    "className":"Simulink.Line",
    "icon":"LineIcon_icon"
   },
   {
    "sid":"estimation_velocity:292#out:1;line",
    "rsid":"estimation_velocity:292#out:1;line",
    "name":"velocity",
    "label":"velocity",
    "className":"Simulink.Line",
    "icon":"LineIcon_icon"
   },
   {
    "sid":"estimation_velocity:291#out:1;line",
    "rsid":"estimation_velocity:291#out:1;line",
    "name":"",
    "label":"",
    "className":"Simulink.Line",
    "icon":"LineIcon_icon"
   },
   {
    "sid":"estimation_velocity:293#out:1;line",
    "rsid":"estimation_velocity:293#out:1;line",
    "name":"",
    "label":"",
    "className":"Simulink.Line",
    "icon":"LineIcon_icon"
   },
   {
    "sid":"estimation_velocity:280#out:1;line",
    "rsid":"estimation_velocity:280#out:1;line",
    "name":"",
    "label":"",
    "className":"Simulink.Line",
    "icon":"LineIcon_icon"
   },
   {
    "sid":"estimation_velocity:299#out:1;line",
    "rsid":"estimation_velocity:299#out:1;line",
    "name":"",
    "label":"",
    "className":"Simulink.Line",
    "icon":"LineIcon_icon"
   }
  ],
  "sysViewURL":"support/slwebview_files/estimation_velocity_d.json",
  "sameAsElement":false
 },
 {
  "hid":520,
  "sid":"estimation_velocity:284",
  "rsid":"estimation_velocity:284",
  "esid":"estimation_velocity:284",
  "parent":519,
  "children":[
   521,
   522,
   523
  ],
  "name":"Least Squares\nPolynomial Fit",
  "fullname":"AMC_BLDC/Motion Controller Single (motion_controller_single)/Motion Controller (motion_controller)/Estimation/Velocity Estimator (estimation_velocity)/Least Squares Polynomial Fit",
  "label":"Least Squares Polynomial Fit",
  "className":"Least Squares Polynomial Fit",
  "icon":"BlockIcon_icon",
  "svg":"support/slwebview_files/estimation_velocity_284_d.svg",
  "thumbnail":"support/slwebview_files/estimation_velocity_284_d.png",
  "elements":[
   {
    "sid":"estimation_velocity:284:2",
    "rsid":"estimation_velocity:284:2",
    "name":"Y",
    "label":"Y",
    "className":"Simulink.Inport",
    "icon":"BlockIcon_icon"
   },
   {
    "sid":"estimation_velocity:284:3",
    "rsid":"estimation_velocity:284:3",
    "name":"Check Signal\nAttributes",
    "label":"Check Signal Attributes",
    "className":"Check Signal Attributes",
    "icon":"BlockIcon_icon"
   },
   {
    "sid":"estimation_velocity:284:4",
    "rsid":"estimation_velocity:284:4",
    "name":"Check Signal\nAttributes1",
    "label":"Check Signal Attributes1",
    "className":"Check Signal Attributes",
    "icon":"BlockIcon_icon"
   },
   {
    "sid":"estimation_velocity:284:5",
    "rsid":"estimation_velocity:284:5",
    "name":"Check Signal\nAttributes2",
    "label":"Check Signal Attributes2",
    "className":"Check Signal Attributes",
    "icon":"BlockIcon_icon"
   },
   {
    "sid":"estimation_velocity:284:6",
    "rsid":"estimation_velocity:284:6",
    "name":"Constant",
    "label":"Constant",
    "className":"Simulink.Constant",
    "icon":"BlockIcon_icon"
   },
   {
    "sid":"estimation_velocity:284:13",
    "rsid":"estimation_velocity:284:13",
    "name":"QR Solver",
    "label":"QR Solver",
    "className":"Simulink.MATLABSystem",
    "icon":"BlockIcon_icon"
   },
   {
    "sid":"estimation_velocity:284:8",
    "rsid":"estimation_velocity:284:8",
    "name":"Out",
    "label":"Out",
    "className":"Simulink.Outport",
    "icon":"BlockIcon_icon"
   },
   {
    "sid":"estimation_velocity:284:5#out:1;line",
    "rsid":"estimation_velocity:284:5#out:1;line",
    "name":"",
    "label":"",
    "className":"Simulink.Line",
    "icon":"LineIcon_icon"
   },
   {
    "sid":"estimation_velocity:284:4#out:1;line",
    "rsid":"estimation_velocity:284:4#out:1;line",
    "name":"",
    "label":"",
    "className":"Simulink.Line",
    "icon":"LineIcon_icon"
   },
   {
    "sid":"estimation_velocity:284:3#out:1;line",
    "rsid":"estimation_velocity:284:3#out:1;line",
    "name":"",
    "label":"",
    "className":"Simulink.Line",
    "icon":"LineIcon_icon"
   },
   {
    "sid":"estimation_velocity:284:6#out:1;line",
    "rsid":"estimation_velocity:284:6#out:1;line",
    "name":"",
    "label":"",
    "className":"Simulink.Line",
    "icon":"LineIcon_icon"
   },
   {
    "sid":"estimation_velocity:284:13#out:1;line",
    "rsid":"estimation_velocity:284:13#out:1;line",
    "name":"",
    "label":"",
    "className":"Simulink.Line",
    "icon":"LineIcon_icon"
   },
   {
    "sid":"estimation_velocity:284:2#out:1;line",
    "rsid":"estimation_velocity:284:2#out:1;line",
    "name":"",
    "label":"",
    "className":"Simulink.Line",
    "icon":"LineIcon_icon"
   }
  ],
  "sysViewURL":"support/slwebview_files/estimation_velocity_284_d.json",
  "sameAsElement":false
 },
 {
  "hid":521,
  "sid":"estimation_velocity:284:3",
  "rsid":"estimation_velocity:284:3",
  "esid":"estimation_velocity:284:3",
  "parent":520,
  "children":[
  ],
  "name":"Check Signal\nAttributes",
  "fullname":"AMC_BLDC/Motion Controller Single (motion_controller_single)/Motion Controller (motion_controller)/Estimation/Velocity Estimator (estimation_velocity)/Least Squares Polynomial Fit/Check Signal Attributes",
  "label":"Check Signal Attributes",
  "className":"Check Signal Attributes",
  "icon":"BlockIcon_icon",
  "svg":"support/slwebview_files/estimation_velocity_284_3_d.svg",
  "thumbnail":"support/slwebview_files/estimation_velocity_284_3_d.png",
  "elements":[
   {
    "sid":"estimation_velocity:284:3:1",
    "rsid":"estimation_velocity:284:3:1",
    "name":"In1",
    "label":"In1",
    "className":"Simulink.Inport",
    "icon":"BlockIcon_icon"
   },
   {
    "sid":"estimation_velocity:284:3:2",
    "rsid":"estimation_velocity:284:3:2",
    "name":"Check Signal\nAttributes",
    "label":"Check Signal Attributes",
    "className":"Simulink.SFunction",
    "icon":"BlockIcon_icon"
   },
   {
    "sid":"estimation_velocity:284:3:3",
    "rsid":"estimation_velocity:284:3:3",
    "name":"Out1",
    "label":"Out1",
    "className":"Simulink.Outport",
    "icon":"BlockIcon_icon"
   },
   {
    "sid":"estimation_velocity:284:3:1#out:1;line",
    "rsid":"estimation_velocity:284:3:1#out:1;line",
    "name":"",
    "label":"",
    "className":"Simulink.Line",
    "icon":"LineIcon_icon"
   }
  ],
  "sysViewURL":"support/slwebview_files/estimation_velocity_284_3_d.json",
  "sameAsElement":false
 },
 {
  "hid":522,
  "sid":"estimation_velocity:284:4",
  "rsid":"estimation_velocity:284:4",
  "esid":"estimation_velocity:284:4",
  "parent":520,
  "children":[
  ],
  "name":"Check Signal\nAttributes1",
  "fullname":"AMC_BLDC/Motion Controller Single (motion_controller_single)/Motion Controller (motion_controller)/Estimation/Velocity Estimator (estimation_velocity)/Least Squares Polynomial Fit/Check Signal Attributes1",
  "label":"Check Signal Attributes1",
  "className":"Check Signal Attributes",
  "icon":"BlockIcon_icon",
  "svg":"support/slwebview_files/estimation_velocity_284_4_d.svg",
  "thumbnail":"support/slwebview_files/estimation_velocity_284_4_d.png",
  "elements":[
   {
    "sid":"estimation_velocity:284:4:1",
    "rsid":"estimation_velocity:284:4:1",
    "name":"In1",
    "label":"In1",
    "className":"Simulink.Inport",
    "icon":"BlockIcon_icon"
   },
   {
    "sid":"estimation_velocity:284:4:2",
    "rsid":"estimation_velocity:284:4:2",
    "name":"Check Signal\nAttributes",
    "label":"Check Signal Attributes",
    "className":"Simulink.SFunction",
    "icon":"BlockIcon_icon"
   },
   {
    "sid":"estimation_velocity:284:4:3",
    "rsid":"estimation_velocity:284:4:3",
    "name":"Out1",
    "label":"Out1",
    "className":"Simulink.Outport",
    "icon":"BlockIcon_icon"
   },
   {
    "sid":"estimation_velocity:284:4:1#out:1;line",
    "rsid":"estimation_velocity:284:4:1#out:1;line",
    "name":"",
    "label":"",
    "className":"Simulink.Line",
    "icon":"LineIcon_icon"
   }
  ],
  "sysViewURL":"support/slwebview_files/estimation_velocity_284_4_d.json",
  "sameAsElement":false
 },
 {
  "hid":523,
  "sid":"estimation_velocity:284:5",
  "rsid":"estimation_velocity:284:5",
  "esid":"estimation_velocity:284:5",
  "parent":520,
  "children":[
  ],
  "name":"Check Signal\nAttributes2",
  "fullname":"AMC_BLDC/Motion Controller Single (motion_controller_single)/Motion Controller (motion_controller)/Estimation/Velocity Estimator (estimation_velocity)/Least Squares Polynomial Fit/Check Signal Attributes2",
  "label":"Check Signal Attributes2",
  "className":"Check Signal Attributes",
  "icon":"BlockIcon_icon",
  "svg":"support/slwebview_files/estimation_velocity_284_5_d.svg",
  "thumbnail":"support/slwebview_files/estimation_velocity_284_5_d.png",
  "elements":[
   {
    "sid":"estimation_velocity:284:5:1",
    "rsid":"estimation_velocity:284:5:1",
    "name":"In1",
    "label":"In1",
    "className":"Simulink.Inport",
    "icon":"BlockIcon_icon"
   },
   {
    "sid":"estimation_velocity:284:5:2",
    "rsid":"estimation_velocity:284:5:2",
    "name":"Check Signal\nAttributes",
    "label":"Check Signal Attributes",
    "className":"Simulink.SFunction",
    "icon":"BlockIcon_icon"
   },
   {
    "sid":"estimation_velocity:284:5:3",
    "rsid":"estimation_velocity:284:5:3",
    "name":"Out1",
    "label":"Out1",
    "className":"Simulink.Outport",
    "icon":"BlockIcon_icon"
   },
   {
    "sid":"estimation_velocity:284:5:1#out:1;line",
    "rsid":"estimation_velocity:284:5:1#out:1;line",
    "name":"",
    "label":"",
    "className":"Simulink.Line",
    "icon":"LineIcon_icon"
   }
  ],
  "sysViewURL":"support/slwebview_files/estimation_velocity_284_5_d.json",
  "sameAsElement":false
 }
]